octo_pipeline_python/backends/clang/__init__.py
octo_pipeline_python/backends/clang/clang_backend.py
octo_pipeline_python/backends/clang/actions/__init__.py
octo_pipeline_python/backends/clang/actions/clang_format_lint_checks.py
octo_pipeline_python/backends/clang/models/__init__.py
octo_pipeline_python/backends/clang/models/clang_model.py
octo_pipeline_backend_clang_python-1.3.2.dist-info/LICENSE.txt
octo_pipeline_backend_clang_python-1.3.2.dist-info/METADATA
octo_pipeline_backend_clang_python-1.3.2.dist-info/README.md
octo_pipeline_backend_clang_python-1.3.2.dist-info/WHEEL
octo_pipeline_backend_clang_python-1.3.2.dist-info/top_level.txt
octo_pipeline_backend_clang_python-1.3.2.dist-info/RECORD
